movoid_log/__init__.py
movoid_log/log.py
movoid_log/log_old.py
movoid_log/logger.py
movoid_log-1.2.6.dist-info/METADATA
movoid_log-1.2.6.dist-info/WHEEL
movoid_log-1.2.6.dist-info/top_level.txt
movoid_log-1.2.6.dist-info/RECORD
