Metadata-Version: 2.4
Name: movoid_log
Version: 1.2.6
Summary: create log
Home-page: 
Author: movoid
Author-email: bobrobotsun@163.com
Requires-Dist: movoid_function
Requires-Dist: movoid_timer
Dynamic: author
Dynamic: author-email
Dynamic: description
Dynamic: description-content-type
Dynamic: requires-dist
Dynamic: summary
